Metadata-Version: 1.2
Name: MetaPathways
Version: 3.1.6
Summary: MetaPathways is a modular pipeline to build PGDBs from Metagenomic sequences.
Home-page: http://packages.python.org/
Author: Kishori Mohan Konwar
Author-email: kishori82@gmail.com
License: MIT
Download-URL: https://github.com/kishori82/MetaPathways_Python.3.0/archive/kmk-develop.zip
Keywords: metagenomics pipeline
Platform: UNKNOWN
Classifier: Development Status :: 2 - Pre-Alpha
Classifier: Environment :: Console
Classifier: Intended Audience :: Science/Research
Classifier: Natural Language :: English
Classifier: License :: OSI Approved :: MIT License
Classifier: Operating System :: POSIX :: Linux
Classifier: Operating System :: MacOS :: MacOS X
Classifier: Programming Language :: Python :: 3.5
Classifier: Topic :: Scientific/Engineering :: Bio-Informatics
Requires-Python: >3.5.2
